yyyutils/Markdown_utils.py
yyyutils/PDF_utils.py
yyyutils/__init__.py
yyyutils/data_structure_utils.py
yyyutils/database_utils.py
yyyutils/decorator_utils.py
yyyutils/engineer_measure_utils.py
yyyutils/excel_utils.py
yyyutils/image_utils.py
yyyutils/json_utils.py
yyyutils/meta_class_utils.py
yyyutils/multiprocesses.py
yyyutils/multithreads.py
yyyutils/os_utils.py
yyyutils/other_tools.py
yyyutils/plot_utils.py
yyyutils/print_utils.py
yyyutils/process_utils.py
yyyutils/regex_utils.py
yyyutils/reinforcement_learning_utils.py
yyyutils/send_message_utils.py
yyyutils/str_formula_to_LaTex.py
yyyutils/test.py
yyyutils/window_utils.py
yyyutils/word_utils.py
yyyutils/word解析替换库.py
yyyutils/xml_html_utils.py
yyyutils/auto_utils/__init__.py
yyyutils/auto_utils/auto_press.py
yyyutils/auto_utils/mouse_utils.py
yyyutils/auto_utils/poe.py
yyyutils/auto_utils/auto/__init__.py
yyyutils/auto_utils/auto/automation_utils.py
yyyutils/auto_utils/auto_click/__init__.py
yyyutils/auto_utils/auto_click/auto_click_by_image_utils.py
yyyutils/auto_utils/auto_click/auto_click_by_point_utils.py
yyyutils/auto_utils/auto_click/new_acbi_utils.py
yyyutils/auto_utils/moniter/__init__.py
yyyutils/auto_utils/moniter/moniter_keyboard_utils.py
yyyutils/auto_utils/moniter/moniter_mouse_utils.py
yyyutils/civil_engineer_utils/__init__.py
yyyutils/civil_engineer_utils/Concrete_design_principles/__init__.py
yyyutils/civil_engineer_utils/Concrete_design_principles/偏心受力构件正截面承载力计算与设计.py
yyyutils/civil_engineer_utils/Concrete_design_principles/受弯构件斜截面性能与承载力计算.py
yyyutils/civil_engineer_utils/Concrete_design_principles/受弯构件正截面承载力计算.py
yyyutils/civil_engineer_utils/Concrete_design_principles/课程设计.py
yyyutils/civil_engineer_utils/Concrete_design_principles/轴心受力构件正截面承载力.py
yyyutils/civil_engineer_utils/Concrete_design_principles/钢筋混凝土构件使用性能与耐久性.py
yyyutils/civil_engineer_utils/Concrete_design_principles/预应力混凝土构件的设计计算.py
yyyutils/civil_engineer_utils/Engineering_survey/__init__.py
yyyutils-1.1.5.dist-info/LICENSE.txt
yyyutils-1.1.5.dist-info/METADATA
yyyutils-1.1.5.dist-info/WHEEL
yyyutils-1.1.5.dist-info/top_level.txt
yyyutils-1.1.5.dist-info/RECORD
