Metadata-Version: 2.2
Name: yyyutils
Version: 1.1.5
Summary: A light weight command line menu that supports Windows, MacOS, and Linux
Author: kyw
Author-email: 
License: GPL-3.0
Keywords: python,utils
Classifier: Development Status :: 1 - Planning
Classifier: Intended Audience :: Developers
Classifier: Programming Language :: Python :: 3
Classifier: Operating System :: Microsoft :: Windows
License-File: LICENSE.txt
Requires-Dist: lxml
Requires-Dist: colorama
Requires-Dist: matplotlib
Requires-Dist: numpy
Requires-Dist: openpyxl
Requires-Dist: psutil
Requires-Dist: python-docx
Requires-Dist: mysql-connector-python
Requires-Dist: comtypes
Requires-Dist: sortedcontainers
Requires-Dist: Pillow
Requires-Dist: loguru
Requires-Dist: keyboard
Requires-Dist: sympy
Dynamic: author
Dynamic: classifier
Dynamic: description
Dynamic: description-content-type
Dynamic: keywords
Dynamic: license
Dynamic: requires-dist
Dynamic: summary
